ABCParse/__init__.py
ABCParse/__version__.py
ABCParse/_abc_parse.py
ABCParse/_as_list.py
ABCParse/_function_kwargs.py
ABCParse/logging/__init__.py
ABCParse/logging/_abc_logger.py
ABCParse/logging/_convenience_functions.py
ABCParse/logging/_format.py
ABCParse/logging/_get_logger.py
ABCParse/logging/_set_global_log_level.py
abcparse-0.1.4.dist-info/LICENSE
abcparse-0.1.4.dist-info/METADATA
abcparse-0.1.4.dist-info/WHEEL
abcparse-0.1.4.dist-info/top_level.txt
abcparse-0.1.4.dist-info/RECORD
